snowconvert_export_sqlserver-0.0.18.data/scripts/sc-sqlserver-arrange
snowconvert_export_sqlserver-0.0.18.data/scripts/sc-sqlserver-arrange.bat
snowconvert_export_sqlserver-0.0.18.data/scripts/sc-sqlserver-export
snowconvert_export_sqlserver-0.0.18.data/scripts/sc-sqlserver-export.ps1
sqlarrange/__init__.py
sqlarrange/__main__.py
sqlarrange/bin/linux64/ExtractionCleanUp
sqlarrange/bin/mac64/ExtractionCleanUp
sqlarrange/bin/win64/ExtractionCleanUp.exe
sqlarrange/bin/win64/Microsoft.Data.SqlClient.SNI.pdb
snowconvert_export_sqlserver-0.0.18.dist-info/LICENSE.txt
snowconvert_export_sqlserver-0.0.18.dist-info/METADATA
snowconvert_export_sqlserver-0.0.18.dist-info/WHEEL
snowconvert_export_sqlserver-0.0.18.dist-info/top_level.txt
snowconvert_export_sqlserver-0.0.18.dist-info/zip-safe
snowconvert_export_sqlserver-0.0.18.dist-info/RECORD
