Metadata-Version: 2.1
Name: snowconvert-export-sqlserver
Version: 0.0.18
Summary: Mobilize.Net SQLServer Export Tool for SnowConvert
Home-page: https://github.com/mobilize/SnowConvertDDLExportScripts/SQLServer
Author: Mobilize.Net
Author-email: mauricio.rojas@mobilize.net
License: MIT
Project-URL: Bug Tracker, https://github.com/MobilizeNet/SnowConvertDDLExportScripts/issues
Platform: UNKNOWN
Classifier: Development Status :: 3 - Alpha
Classifier: Intended Audience :: Developers
Classifier: Intended Audience :: System Administrators
Classifier: Programming Language :: Python
Classifier: Programming Language :: Python :: 2
Classifier: Programming Language :: Python :: 2.7
Classifier: Programming Language :: Python :: 3
Classifier: Programming Language :: Python :: 3.4
Classifier: Programming Language :: Python :: 3.5
Classifier: Programming Language :: Python :: 3.6
Classifier: License :: OSI Approved :: MIT License
License-File: LICENSE.txt
Requires-Dist: mssql-scripter
Requires-Dist: future (>=0.16.0)
Requires-Dist: wheel (>=0.29.0)
